knox_engine.py
knoxscript-0.1.3.dist-info/METADATA
knoxscript-0.1.3.dist-info/WHEEL
knoxscript-0.1.3.dist-info/entry_points.txt
knoxscript-0.1.3.dist-info/top_level.txt
knoxscript-0.1.3.dist-info/RECORD
