Metadata-Version: 2.4
Name: knoxscript
Version: 0.1.3
Requires-Dist: opencv-python
Requires-Dist: numpy
Dynamic: requires-dist
